gauss/__init__.py
gauss/core.py
gauss/linear.py
gauss/vec.py
gauss/lib/__init__.py
gauss/lib/libgauss.so
gauss-0.0.9.dist-info/LICENSE
gauss-0.0.9.dist-info/METADATA
gauss-0.0.9.dist-info/WHEEL
gauss-0.0.9.dist-info/top_level.txt
gauss-0.0.9.dist-info/zip-safe
gauss-0.0.9.dist-info/RECORD
