Metadata-Version: 2.1
Name: gauss
Version: 0.0.9
Summary: Python bindings for Gauss (General Algorithmic Unified Statistical Solvers)
Home-page: https://github.com/kkloberdanz/pygauss
Author: Kyle Kloberdanz
Author-email: kyle.g.kloberdanz@gmail.com
License: UNKNOWN
Platform: UNKNOWN
Classifier: Programming Language :: Python :: 3
Classifier: License :: OSI Approved :: MIT License
Classifier: Operating System :: OS Independent
Requires-Python: >=3.6
